{
	"tool": "jekyll",
	"source": "implementationguide/hl7-fhir-us-hai-ltcf.xml",
	"npm-name": "hl7.fhir.us.hai-ltcf",
	"license": "CC0-1.0",
	"paths": {
	  "history": "http://hl7.org/fhir/us/hai-ltcf/history.cfml",
		"qa": "generated_output/qa",
		"temp": "generated_output/temp",
		"output": "output",
		"txCache": "generated_output/txCache",
		"specification": "http://hl7.org/fhir/R4/",
		"pages": [
			"framework",
			"source/pages"
		],
		"resources": [
			"source/resources"
		]
	},
	"pages": [
		"pages"
	],
	"extension-domains": [
		"https://trifolia-on-fhir.lantanagroup.com"
	],
	"allowed-domains": [
		"https://trifolia-on-fhir.lantanagroup.com"
	],
	"sct-edition": "http://snomed.info/sct/731000124108",
	"canonicalBase": "http://hl7.org/fhir/us/hai-ltcf",
	"defaults": {
		"Location": {
			"template-base": "ex.html"
		},
		"ProcedureRequest": {
			"template-base": "ex.html"
		},
		"Organization": {
			"template-base": "ex.html"
		},
		"MedicationStatement": {
			"template-base": "ex.html"
		},
		"SearchParameter": {
			"template-base": "base.html"
		},
		"StructureDefinition": {
			"template-mappings": "sd-mappings.html",
			"template-base": "sd.html",
			"template-defns": "sd-definitions.html"
		},
		"Immunization": {
			"template-base": "ex.html"
		},
		"Patient": {
			"template-base": "ex.html"
		},
		"StructureMap": {
			"content": false,
			"script": false,
			"template-base": "ex.html",
			"profiles": false
		},
		"ConceptMap": {
			"template-base": "base.html"
		},
		"Practitioner": {
			"template-base": "ex.html"
		},
		"OperationDefinition": {
			"template-base": "base.html"
		},
		"CodeSystem": {
			"template-base": "base.html"
		},
		"Communication": {
			"template-base": "ex.html"
		},
		"Any": {
			"template-format": "format.html",
			"template-base": "base.html"
		},
		"PractitionerRole": {
			"template-base": "ex.html"
		},
		"ValueSet": {
			"template-base": "base.html"
		},
		"CapabilityStatement": {
			"template-base": "base.html"
		},
		"Observation": {
			"template-base": "ex.html"
		}
	},
	"resources": {
		"Group/hai-ltcf-group-1": {
			"base": "Group-hai-ltcf-group-1.html",
			"defns": "Group-hai-ltcf-group-1-definitions.html"
		},
		"Patient/hai-ltcf-resident-1": {
			"base": "Patient-hai-ltcf-resident-1.html",
			"defns": "Patient-hai-ltcf-resident-1-definitions.html"
		},
		"Questionnaire/hai-ltcf-questionnaire-mdro-cdi-summary": {
			"base": "Questionnaire-hai-ltcf-questionnaire-mdro-cdi-summary.html",
			"defns": "Questionnaire-hai-ltcf-questionnaire-mdro-cdi-summary-definitions.html"
		},
		"Questionnaire/hai-ltcf-questionnaire-mdro-cdi-event": {
			"base": "Questionnaire-hai-ltcf-questionnaire-mdro-cdi-event.html",
			"defns": "Questionnaire-hai-ltcf-questionnaire-mdro-cdi-event-definitions.html"
		},
		"QuestionnaireResponse/hai-ltcf-questionnaireresponse-mdro-cdi-event": {
			"base": "QuestionnaireResponse-hai-ltcf-questionnaireresponse-mdro-cdi-event.html",
			"defns": "QuestionnaireResponse-hai-ltcf-questionnaireresponse-mdro-cdi-event-definitions.html"
		},
		"QuestionnaireResponse/hai-ltcf-questionnaireresponse-mdro-cdi-summary": {
			"base": "QuestionnaireResponse-hai-ltcf-questionnaireresponse-mdro-cdi-summary.html",
			"defns": "QuestionnaireResponse-hai-ltcf-questionnaireresponse-mdro-cdi-summary-definitions.html"
		},
		"Device/hai-ltcf-authoring-device": {
			"base": "Device-hai-ltcf-authoring-device.html",
			"defns": "Device-hai-ltcf-authoring-device-definitions.html"
		},
		"CodeSystem/2.16.840.1.113883.6.259": {
			"base": "CodeSystem-2.16.840.1.113883.6.259.html",
			"defns": "CodeSystem-2.16.840.1.113883.6.259.html"
		},
		"CodeSystem/2.16.840.1.113883.6.277": {
			"base": "CodeSystem-2.16.840.1.113883.6.277.html",
			"defns": "CodeSystem-2.16.840.1.113883.6.277.html"
		}
	},
	"version": "4.0.1",
	"fixed-business-version": "0.1.0",
	"dependencyList": [
		{
			"location": "http://hl7.org/fhir/us/core",
			"name": "USCoreR4",
			"version": "3.0.0",
			"package": "hl7.fhir.us.core"
		},
		{
			"location": "http://hl7.org/fhir/us/hai",
			"name": "NHSN Healthcare Associated Infection (HAI) Reports",
			"version": "2.0.0",
			"package": "hl7.fhir.us.hai"
		}
	]
}